{"action":{"identity":{"address":"N\u0000sourcecred\u0000core\u0000IDENTITY\u0000Kgx1ukWNAp6RlQVeqFpYNA\u0000","aliases":[],"id":"Kgx1ukWNAp6RlQVeqFpYNA","name":"system","subtype":"BOT"},"type":"CREATE_IDENTITY"},"ledgerTimestamp":1637973810016,"uuid":"Bs4P96QkVJhRgtLW812U4g","version":"1"}
{"action":{"alias":{"address":"N\u0000sourcecred\u0000discourse\u0000user\u0000https://forum.radstarter.io\u0000system\u0000","description":"discourse/[@system](https://forum.radstarter.io/u/system/)"},"identityId":"Kgx1ukWNAp6RlQVeqFpYNA","type":"ADD_ALIAS"},"ledgerTimestamp":1637973810017,"uuid":"o3hkh2j5z56VJVEVXGYwWA","version":"1"}
{"action":{"identity":{"address":"N\u0000sourcecred\u0000core\u0000IDENTITY\u0000S0upAwmuDQ9i2XOTx0EcRQ\u0000","aliases":[],"id":"S0upAwmuDQ9i2XOTx0EcRQ","name":"GreatApe","subtype":"USER"},"type":"CREATE_IDENTITY"},"ledgerTimestamp":1637973810018,"uuid":"a1o6czoxt3eqOam7a7vXxA","version":"1"}
{"action":{"alias":{"address":"N\u0000sourcecred\u0000discourse\u0000user\u0000https://forum.radstarter.io\u0000GreatApe\u0000","description":"discourse/[@GreatApe](https://forum.radstarter.io/u/GreatApe/)"},"identityId":"S0upAwmuDQ9i2XOTx0EcRQ","type":"ADD_ALIAS"},"ledgerTimestamp":1637973810018,"uuid":"LbmvujFzmxMr2DRnyRs4dQ","version":"1"}
{"action":{"identity":{"address":"N\u0000sourcecred\u0000core\u0000IDENTITY\u0000YpOz3TpnZ8xQ5GQqJ2X1gg\u0000","aliases":[],"id":"YpOz3TpnZ8xQ5GQqJ2X1gg","name":"officiallytimewasted","subtype":"USER"},"type":"CREATE_IDENTITY"},"ledgerTimestamp":1637973810018,"uuid":"iZV7329x6vCDSlMoCoOPUg","version":"1"}
{"action":{"alias":{"address":"N\u0000sourcecred\u0000discourse\u0000user\u0000https://forum.radstarter.io\u0000officiallytimewasted\u0000","description":"discourse/[@officiallytimewasted](https://forum.radstarter.io/u/officiallytimewasted/)"},"identityId":"YpOz3TpnZ8xQ5GQqJ2X1gg","type":"ADD_ALIAS"},"ledgerTimestamp":1637973810019,"uuid":"nEgExw5FXViPPbtkyI14PQ","version":"1"}
{"action":{"identity":{"address":"N\u0000sourcecred\u0000core\u0000IDENTITY\u0000fzAk8D4KkKXV0uyPK1cEQw\u0000","aliases":[],"id":"fzAk8D4KkKXV0uyPK1cEQw","name":"Jafaroff","subtype":"USER"},"type":"CREATE_IDENTITY"},"ledgerTimestamp":1637973810019,"uuid":"Igp3KoWzaktlfGUeQpUzjw","version":"1"}
{"action":{"alias":{"address":"N\u0000sourcecred\u0000discourse\u0000user\u0000https://forum.radstarter.io\u0000Jafaroff\u0000","description":"discourse/[@Jafaroff](https://forum.radstarter.io/u/Jafaroff/)"},"identityId":"fzAk8D4KkKXV0uyPK1cEQw","type":"ADD_ALIAS"},"ledgerTimestamp":1637973810019,"uuid":"G6umGUEwMATyQ2mq3E4H7g","version":"1"}
{"action":{"identity":{"address":"N\u0000sourcecred\u0000core\u0000IDENTITY\u00000UYqgMc5QEjl3vBH9xQTyQ\u0000","aliases":[],"id":"0UYqgMc5QEjl3vBH9xQTyQ","name":"Miso","subtype":"USER"},"type":"CREATE_IDENTITY"},"ledgerTimestamp":1637973810019,"uuid":"oQvUMaUNLDDSVIy0eHXVGg","version":"1"}
{"action":{"alias":{"address":"N\u0000sourcecred\u0000discourse\u0000user\u0000https://forum.radstarter.io\u0000Miso\u0000","description":"discourse/[@Miso](https://forum.radstarter.io/u/Miso/)"},"identityId":"0UYqgMc5QEjl3vBH9xQTyQ","type":"ADD_ALIAS"},"ledgerTimestamp":1637973810020,"uuid":"HxzIEdvEiyirN9xSpZlO9Q","version":"1"}
{"action":{"identity":{"address":"N\u0000sourcecred\u0000core\u0000IDENTITY\u0000Zk2AyX0T8lPtJ2N2OAlvsQ\u0000","aliases":[],"id":"Zk2AyX0T8lPtJ2N2OAlvsQ","name":"dRAT3","subtype":"USER"},"type":"CREATE_IDENTITY"},"ledgerTimestamp":1637973810020,"uuid":"Q0G0hDTrSWF92QdupfExBA","version":"1"}
{"action":{"alias":{"address":"N\u0000sourcecred\u0000discourse\u0000user\u0000https://forum.radstarter.io\u0000dRAT3\u0000","description":"discourse/[@dRAT3](https://forum.radstarter.io/u/dRAT3/)"},"identityId":"Zk2AyX0T8lPtJ2N2OAlvsQ","type":"ADD_ALIAS"},"ledgerTimestamp":1637973810020,"uuid":"TGmzx6hzvZvkE9zYo8Qlug","version":"1"}
{"action":{"identity":{"address":"N\u0000sourcecred\u0000core\u0000IDENTITY\u0000sqyKMQgckcqnNmKu6vRQJA\u0000","aliases":[],"id":"sqyKMQgckcqnNmKu6vRQJA","name":"Rock-Howard","subtype":"USER"},"type":"CREATE_IDENTITY"},"ledgerTimestamp":1637973810165,"uuid":"FqKJPo3a84FwwP1S2IgcEg","version":"1"}
{"action":{"alias":{"address":"N\u0000sourcecred\u0000discord\u0000MEMBER\u0000user\u0000198451964370092032\u0000","description":"discord/Rock-Howard#8203"},"identityId":"sqyKMQgckcqnNmKu6vRQJA","type":"ADD_ALIAS"},"ledgerTimestamp":1637973810165,"uuid":"KQ0vBeOn4n1FXk7QYQMLjw","version":"1"}
{"action":{"identity":{"address":"N\u0000sourcecred\u0000core\u0000IDENTITY\u00003V0MeQAnaunubkpspln9YA\u0000","aliases":[],"id":"3V0MeQAnaunubkpspln9YA","name":"dRAT3-discord","subtype":"USER"},"type":"CREATE_IDENTITY"},"ledgerTimestamp":1637973810166,"uuid":"8iBtRllLVcg1maozDLD8nA","version":"1"}
{"action":{"alias":{"address":"N\u0000sourcecred\u0000discord\u0000MEMBER\u0000user\u0000741214806459285514\u0000","description":"discord/dRAT3#6925"},"identityId":"3V0MeQAnaunubkpspln9YA","type":"ADD_ALIAS"},"ledgerTimestamp":1637973810166,"uuid":"XSng8T3062hx7LlvMorVqA","version":"1"}
{"action":{"identity":{"address":"N\u0000sourcecred\u0000core\u0000IDENTITY\u0000S18fjPt88X1HAGd8gTaAjw\u0000","aliases":[],"id":"S18fjPt88X1HAGd8gTaAjw","name":"JCrypto","subtype":"USER"},"type":"CREATE_IDENTITY"},"ledgerTimestamp":1637973810166,"uuid":"AZeB3dkzGTxWj5sYo1tlUA","version":"1"}
{"action":{"alias":{"address":"N\u0000sourcecred\u0000discord\u0000MEMBER\u0000user\u0000768164126635589663\u0000","description":"discord/JCrypto#1840"},"identityId":"S18fjPt88X1HAGd8gTaAjw","type":"ADD_ALIAS"},"ledgerTimestamp":1637973810166,"uuid":"OVj276HZkmd4ubJvSLmaiw","version":"1"}
{"action":{"identity":{"address":"N\u0000sourcecred\u0000core\u0000IDENTITY\u0000xbbFGv2EEZF3Rqg9EoRlOw\u0000","aliases":[],"id":"xbbFGv2EEZF3Rqg9EoRlOw","name":"Sea-Mine124","subtype":"USER"},"type":"CREATE_IDENTITY"},"ledgerTimestamp":1637973810167,"uuid":"3bM5aIPDKtqqEUrHQorZCA","version":"1"}
{"action":{"alias":{"address":"N\u0000sourcecred\u0000discord\u0000MEMBER\u0000user\u0000890627679496306708\u0000","description":"discord/Sea-Mine124#3826"},"identityId":"xbbFGv2EEZF3Rqg9EoRlOw","type":"ADD_ALIAS"},"ledgerTimestamp":1637973810167,"uuid":"BOD7dbC1i3Mzyy1wJEPF8A","version":"1"}
{"action":{"identity":{"address":"N\u0000sourcecred\u0000core\u0000IDENTITY\u0000Mqwr4I2hqUeDGE25bapJLg\u0000","aliases":[],"id":"Mqwr4I2hqUeDGE25bapJLg","name":"SourceCred-bot","subtype":"BOT"},"type":"CREATE_IDENTITY"},"ledgerTimestamp":1637973810167,"uuid":"m7y7E1LwlT60bwvRr4RfAg","version":"1"}
{"action":{"alias":{"address":"N\u0000sourcecred\u0000discord\u0000MEMBER\u0000bot\u0000903861366702628954\u0000","description":"discord/SourceCred-bot#9906"},"identityId":"Mqwr4I2hqUeDGE25bapJLg","type":"ADD_ALIAS"},"ledgerTimestamp":1637973810168,"uuid":"QrInWlxez0nOrJadlXuJFg","version":"1"}
{"action":{"identity":{"address":"N\u0000sourcecred\u0000core\u0000IDENTITY\u0000Vv8xl8APonpRynarc5nnHA\u0000","aliases":[],"id":"Vv8xl8APonpRynarc5nnHA","name":"Bufu","subtype":"USER"},"type":"CREATE_IDENTITY"},"ledgerTimestamp":1637973810168,"uuid":"bWNxh0owoVo4XOnWwvilPQ","version":"1"}
{"action":{"alias":{"address":"N\u0000sourcecred\u0000discord\u0000MEMBER\u0000user\u0000232054453560279040\u0000","description":"discord/Bufu#5130"},"identityId":"Vv8xl8APonpRynarc5nnHA","type":"ADD_ALIAS"},"ledgerTimestamp":1637973810168,"uuid":"KVtpML4KoQiNyIX5wvs4tg","version":"1"}
{"action":{"identity":{"address":"N\u0000sourcecred\u0000core\u0000IDENTITY\u0000ZjGPaFww9a20LPdrQqC9ZA\u0000","aliases":[],"id":"ZjGPaFww9a20LPdrQqC9ZA","name":"Chris","subtype":"USER"},"type":"CREATE_IDENTITY"},"ledgerTimestamp":1637973810169,"uuid":"RNZbK3zhPVfXyNzVQg9kTQ","version":"1"}
{"action":{"alias":{"address":"N\u0000sourcecred\u0000discord\u0000MEMBER\u0000user\u0000248210285339344896\u0000","description":"discord/Chris#5446"},"identityId":"ZjGPaFww9a20LPdrQqC9ZA","type":"ADD_ALIAS"},"ledgerTimestamp":1637973810169,"uuid":"9L7dRMEv4JrtBnaI4m562w","version":"1"}
{"action":{"identity":{"address":"N\u0000sourcecred\u0000core\u0000IDENTITY\u0000nGAjKnLBuvVJyeRdSEB8WA\u0000","aliases":[],"id":"nGAjKnLBuvVJyeRdSEB8WA","name":"Croq","subtype":"USER"},"type":"CREATE_IDENTITY"},"ledgerTimestamp":1637973810169,"uuid":"0C2T4ArO0bTzTl98fbebmQ","version":"1"}
{"action":{"alias":{"address":"N\u0000sourcecred\u0000discord\u0000MEMBER\u0000user\u0000304730500981850112\u0000","description":"discord/Croq#5660"},"identityId":"nGAjKnLBuvVJyeRdSEB8WA","type":"ADD_ALIAS"},"ledgerTimestamp":1637973810169,"uuid":"A4mUK8KQLJAGG9pJ2DmrbA","version":"1"}
{"action":{"identity":{"address":"N\u0000sourcecred\u0000core\u0000IDENTITY\u0000nvAT7koWk8aQj9E5OjDfQg\u0000","aliases":[],"id":"nvAT7koWk8aQj9E5OjDfQg","name":"Loliver","subtype":"USER"},"type":"CREATE_IDENTITY"},"ledgerTimestamp":1637973810170,"uuid":"OLGsJXkuAKenZGmfnKO5Fw","version":"1"}
{"action":{"alias":{"address":"N\u0000sourcecred\u0000discord\u0000MEMBER\u0000user\u0000337703439171846156\u0000","description":"discord/Loliver#7230"},"identityId":"nvAT7koWk8aQj9E5OjDfQg","type":"ADD_ALIAS"},"ledgerTimestamp":1637973810170,"uuid":"DtBOM7Hkkah0dXAd7McNVQ","version":"1"}
{"action":{"identity":{"address":"N\u0000sourcecred\u0000core\u0000IDENTITY\u0000HqAPxX1fGJWo3KJSW0wBlA\u0000","aliases":[],"id":"HqAPxX1fGJWo3KJSW0wBlA","name":"Miro","subtype":"USER"},"type":"CREATE_IDENTITY"},"ledgerTimestamp":1637973810170,"uuid":"2nRV8a5Cw5m1Vxa5Nd9v6Q","version":"1"}
{"action":{"alias":{"address":"N\u0000sourcecred\u0000discord\u0000MEMBER\u0000user\u0000345944971825774603\u0000","description":"discord/Miro#9879"},"identityId":"HqAPxX1fGJWo3KJSW0wBlA","type":"ADD_ALIAS"},"ledgerTimestamp":1637973810170,"uuid":"GAJOBvK9AOkP6zsQM3FaqQ","version":"1"}
{"action":{"identity":{"address":"N\u0000sourcecred\u0000core\u0000IDENTITY\u0000iDZoJsYxvYEwEEHPgkHWhQ\u0000","aliases":[],"id":"iDZoJsYxvYEwEEHPgkHWhQ","name":"Miso-discord","subtype":"USER"},"type":"CREATE_IDENTITY"},"ledgerTimestamp":1637973810170,"uuid":"BsO6dLMvHBXjQMJhb6aKsg","version":"1"}
{"action":{"alias":{"address":"N\u0000sourcecred\u0000discord\u0000MEMBER\u0000user\u0000378935742342103040\u0000","description":"discord/Miso#6290"},"identityId":"iDZoJsYxvYEwEEHPgkHWhQ","type":"ADD_ALIAS"},"ledgerTimestamp":1637973810171,"uuid":"P5eP3JCe0yJXy7e3WocdzA","version":"1"}
{"action":{"identity":{"address":"N\u0000sourcecred\u0000core\u0000IDENTITY\u0000DylC4IQ1HKmVRr3sqrKQIA\u0000","aliases":[],"id":"DylC4IQ1HKmVRr3sqrKQIA","name":"mindup","subtype":"USER"},"type":"CREATE_IDENTITY"},"ledgerTimestamp":1637973810171,"uuid":"tZyaJwC4W58fgZvgX6uzdg","version":"1"}
{"action":{"alias":{"address":"N\u0000sourcecred\u0000discord\u0000MEMBER\u0000user\u0000384088679314096129\u0000","description":"discord/mindup#2463"},"identityId":"DylC4IQ1HKmVRr3sqrKQIA","type":"ADD_ALIAS"},"ledgerTimestamp":1637973810171,"uuid":"hah1PCGoaPfps882kGh1pA","version":"1"}
{"action":{"identity":{"address":"N\u0000sourcecred\u0000core\u0000IDENTITY\u0000YLztpyw6PbvRGuQJUd3Y0w\u0000","aliases":[],"id":"YLztpyw6PbvRGuQJUd3Y0w","name":"xwf22","subtype":"USER"},"type":"CREATE_IDENTITY"},"ledgerTimestamp":1637973810171,"uuid":"2nuNBxlpcXqEDIb9QURV4A","version":"1"}
{"action":{"alias":{"address":"N\u0000sourcecred\u0000discord\u0000MEMBER\u0000user\u0000402122072064786445\u0000","description":"discord/xwf22#2720"},"identityId":"YLztpyw6PbvRGuQJUd3Y0w","type":"ADD_ALIAS"},"ledgerTimestamp":1637973810171,"uuid":"zR2rZwrYTznkWvO2s46XnQ","version":"1"}
{"action":{"identity":{"address":"N\u0000sourcecred\u0000core\u0000IDENTITY\u0000SlPXZuq8wRbyXgXMhGnJ0A\u0000","aliases":[],"id":"SlPXZuq8wRbyXgXMhGnJ0A","name":"---Marat","subtype":"USER"},"type":"CREATE_IDENTITY"},"ledgerTimestamp":1637973810172,"uuid":"nZOWf5afeQyYgQwnJEbjqQ","version":"1"}
{"action":{"alias":{"address":"N\u0000sourcecred\u0000discord\u0000MEMBER\u0000user\u0000443900463201648670\u0000","description":"discord/---Marat#4660"},"identityId":"SlPXZuq8wRbyXgXMhGnJ0A","type":"ADD_ALIAS"},"ledgerTimestamp":1637973810172,"uuid":"cqZLEiLpwnn33TvHE2xQ1Q","version":"1"}
{"action":{"identity":{"address":"N\u0000sourcecred\u0000core\u0000IDENTITY\u0000prIoNxNEXjaiAQYVtPaI7Q\u0000","aliases":[],"id":"prIoNxNEXjaiAQYVtPaI7Q","name":"Quantman74","subtype":"USER"},"type":"CREATE_IDENTITY"},"ledgerTimestamp":1637973810172,"uuid":"OzF5DHB3eqeBNOfNf65Phw","version":"1"}
{"action":{"alias":{"address":"N\u0000sourcecred\u0000discord\u0000MEMBER\u0000user\u0000529260358972604417\u0000","description":"discord/Quantman74#1379"},"identityId":"prIoNxNEXjaiAQYVtPaI7Q","type":"ADD_ALIAS"},"ledgerTimestamp":1637973810172,"uuid":"Nt5AzrkO2F8KoagbBzqmyg","version":"1"}
{"action":{"identity":{"address":"N\u0000sourcecred\u0000core\u0000IDENTITY\u0000AhG2QaDaFLM1yDe7lbmXcw\u0000","aliases":[],"id":"AhG2QaDaFLM1yDe7lbmXcw","name":"td","subtype":"USER"},"type":"CREATE_IDENTITY"},"ledgerTimestamp":1637973810172,"uuid":"30Ax5J7x6hmeRpbcYO26Ow","version":"1"}
{"action":{"alias":{"address":"N\u0000sourcecred\u0000discord\u0000MEMBER\u0000user\u0000604531607025483826\u0000","description":"discord/td#6993"},"identityId":"AhG2QaDaFLM1yDe7lbmXcw","type":"ADD_ALIAS"},"ledgerTimestamp":1637973810172,"uuid":"oBiRFbPUvBGc3zGXE9klGg","version":"1"}
{"action":{"identity":{"address":"N\u0000sourcecred\u0000core\u0000IDENTITY\u0000U9dx8ik1iEI1DqrIN6ZIkA\u0000","aliases":[],"id":"U9dx8ik1iEI1DqrIN6ZIkA","name":"DaveHen","subtype":"USER"},"type":"CREATE_IDENTITY"},"ledgerTimestamp":1637973810173,"uuid":"7cwfBYWUDMqYE9HVyaEE3g","version":"1"}
{"action":{"alias":{"address":"N\u0000sourcecred\u0000discord\u0000MEMBER\u0000user\u0000738273261502333008\u0000","description":"discord/DaveHen#6676"},"identityId":"U9dx8ik1iEI1DqrIN6ZIkA","type":"ADD_ALIAS"},"ledgerTimestamp":1637973810173,"uuid":"aBgDGop27UGUj6KtD7Atbg","version":"1"}
{"action":{"identity":{"address":"N\u0000sourcecred\u0000core\u0000IDENTITY\u000027JtvSqO1X8MA05qt3CJKg\u0000","aliases":[],"id":"27JtvSqO1X8MA05qt3CJKg","name":"mimi-uxui","subtype":"USER"},"type":"CREATE_IDENTITY"},"ledgerTimestamp":1637973810173,"uuid":"D5JdGuo1YamFD6d6vNeo0A","version":"1"}
{"action":{"alias":{"address":"N\u0000sourcecred\u0000discord\u0000MEMBER\u0000user\u0000795249508933959721\u0000","description":"discord/mimi-uxui#9030"},"identityId":"27JtvSqO1X8MA05qt3CJKg","type":"ADD_ALIAS"},"ledgerTimestamp":1637973810173,"uuid":"xjLWPeWzQKQHYapB8DNdpQ","version":"1"}
{"action":{"identity":{"address":"N\u0000sourcecred\u0000core\u0000IDENTITY\u0000xnDdliKsa0wpG5HyYUqZOA\u0000","aliases":[],"id":"xnDdliKsa0wpG5HyYUqZOA","name":"Jafaroff-discord","subtype":"USER"},"type":"CREATE_IDENTITY"},"ledgerTimestamp":1637973810174,"uuid":"w5BVFN8YbdUy3bqGC8AZAw","version":"1"}
{"action":{"alias":{"address":"N\u0000sourcecred\u0000discord\u0000MEMBER\u0000user\u0000837084008910422047\u0000","description":"discord/Jafaroff#9292"},"identityId":"xnDdliKsa0wpG5HyYUqZOA","type":"ADD_ALIAS"},"ledgerTimestamp":1637973810174,"uuid":"CNzjrcnBLlRQM1kBVJjvjA","version":"1"}
{"action":{"identity":{"address":"N\u0000sourcecred\u0000core\u0000IDENTITY\u0000Ngfva2456mDPg5jzQPu6wg\u0000","aliases":[],"id":"Ngfva2456mDPg5jzQPu6wg","name":"erbsreyes","subtype":"USER"},"type":"CREATE_IDENTITY"},"ledgerTimestamp":1637973810174,"uuid":"ZmZRF3drsMQuZ9kNidj76Q","version":"1"}
{"action":{"alias":{"address":"N\u0000sourcecred\u0000discord\u0000MEMBER\u0000user\u0000862486177059045407\u0000","description":"discord/erbsreyes#2719"},"identityId":"Ngfva2456mDPg5jzQPu6wg","type":"ADD_ALIAS"},"ledgerTimestamp":1637973810174,"uuid":"YpSOGxlKnr7ypLgLjxuqaQ","version":"1"}
{"action":{"identity":{"address":"N\u0000sourcecred\u0000core\u0000IDENTITY\u0000hrZ2OEmapuRTwx3y50vbSw\u0000","aliases":[],"id":"hrZ2OEmapuRTwx3y50vbSw","name":"Dr-moruz","subtype":"USER"},"type":"CREATE_IDENTITY"},"ledgerTimestamp":1637973810174,"uuid":"fAqd3JguEO641brqVEVpHg","version":"1"}
{"action":{"alias":{"address":"N\u0000sourcecred\u0000discord\u0000MEMBER\u0000user\u0000907465361836892241\u0000","description":"discord/Dr-moruz#5120"},"identityId":"hrZ2OEmapuRTwx3y50vbSw","type":"ADD_ALIAS"},"ledgerTimestamp":1637973810174,"uuid":"4LSYgzPKKIxVLmceAq0HrA","version":"1"}
{"action":{"identity":{"address":"N\u0000sourcecred\u0000core\u0000IDENTITY\u0000fa6Fvv8wR6pjD9jBxs32xw\u0000","aliases":[],"id":"fa6Fvv8wR6pjD9jBxs32xw","name":"artaxis","subtype":"USER"},"type":"CREATE_IDENTITY"},"ledgerTimestamp":1637973810174,"uuid":"7cYgQlDeqzVjzMM8eSgx7Q","version":"1"}
{"action":{"alias":{"address":"N\u0000sourcecred\u0000discord\u0000MEMBER\u0000user\u0000907943095872659456\u0000","description":"discord/artaxis#7279"},"identityId":"fa6Fvv8wR6pjD9jBxs32xw","type":"ADD_ALIAS"},"ledgerTimestamp":1637973810174,"uuid":"hzrlmFZodlRCPkflKrYSXw","version":"1"}
{"action":{"identity":{"address":"N\u0000sourcecred\u0000core\u0000IDENTITY\u0000xho5pOQU1ULR1MmSbzPQ1Q\u0000","aliases":[],"id":"xho5pOQU1ULR1MmSbzPQ1Q","name":"dRAT3-github","subtype":"USER"},"type":"CREATE_IDENTITY"},"ledgerTimestamp":1637973810781,"uuid":"JR3V8xKAnz3Q4FBvER2yKw","version":"1"}
{"action":{"alias":{"address":"N\u0000sourcecred\u0000github\u0000USERLIKE\u0000USER\u0000dRAT3\u0000","description":"github/[@dRAT3](https://github.com/dRAT3)"},"identityId":"xho5pOQU1ULR1MmSbzPQ1Q","type":"ADD_ALIAS"},"ledgerTimestamp":1637973810781,"uuid":"OSzup5GTboUJC89Uo6FxBA","version":"1"}
{"action":{"identity":{"address":"N\u0000sourcecred\u0000core\u0000IDENTITY\u0000JMKYEfEd3mu8E66G7hOZQA\u0000","aliases":[],"id":"JMKYEfEd3mu8E66G7hOZQA","name":"SourceCred","subtype":"PROJECT"},"type":"CREATE_IDENTITY"},"ledgerTimestamp":1637973810936,"uuid":"qTG2ZXDrMNG2yvSkwxFxyA","version":"1"}
{"action":{"identityId":"JMKYEfEd3mu8E66G7hOZQA","type":"TOGGLE_ACTIVATION"},"ledgerTimestamp":1637973810936,"uuid":"JCALr5nTQqwIMcWK6upysg","version":"1"}
